ebs_snatcher/__init__.py
ebs_snatcher/ebs.py
ebs_snatcher/main.py
ebs_snatcher/util.py
ebs_snatcher-0.2.0.dist-info/DESCRIPTION.rst
ebs_snatcher-0.2.0.dist-info/METADATA
ebs_snatcher-0.2.0.dist-info/RECORD
ebs_snatcher-0.2.0.dist-info/WHEEL
ebs_snatcher-0.2.0.dist-info/entry_points.txt
ebs_snatcher-0.2.0.dist-info/metadata.json
ebs_snatcher-0.2.0.dist-info/top_level.txt
