Metadata-Version: 2.0
Name: ebs-snatcher
Version: 0.2.0
Summary: Automatically provision AWS EBS volumes from snapshots
Home-page: https://github.com/Cobliteam/ebs-snatcher
Author: Daniel Miranda
Author-email: daniel@cobli.co
License: MIT
Download-URL: https://github.com/Cobliteam/ebs-snatcher/archive/0.2.0.tar.gz
Keywords: aws ebs
Platform: UNKNOWN
Requires-Dist: boto3
Requires-Dist: future
